pdc_python_sdk/__init__.py
pdc_python_sdk/__main__.py
pdc_python_sdk/cmdline.py
pdc_python_sdk/demo.py
pdc_python_sdk/tests/__init__.py
pdc_python_sdk-0.1.0.dist-info/METADATA
pdc_python_sdk-0.1.0.dist-info/WHEEL
pdc_python_sdk-0.1.0.dist-info/top_level.txt
pdc_python_sdk-0.1.0.dist-info/RECORD
