Metadata-Version: 2.1
Name: pdc-python-sdk
Version: 0.1.0
Summary: test
Home-page: http://icode.baidu.com/repos/baidu/personal-code/pdc-python-sdk/tree/master
Author: jiaqianjing
Author-email: jiaqianjing@baidu.com
License: MIT
Platform: UNKNOWN
Classifier: Programming Language :: Python
Classifier: Programming Language :: Python :: 2
Classifier: Programming Language :: Python :: 2.7
